{
    "$defs": {
        "DefId": {
            "type": "string"
        },
        "Ty": {
            "type": "string"
        },
        "Var": {
            "type": "object",
            "required": [
                "is_zst",
                "mut",
                "name",
                "ty"
            ],
            "additionalProperties": false,
            "properties": {
                "is_zst": {
                    "type": "boolean",
                    "description": "Is this a zero size type?"
                },
                "mut": {
                    "$ref": "#/$defs/Mutability"
                },
                "name": {
                    "type": "string"
                },
                "ty": {
                    "$ref": "#/$defs/Ty"
                }
            }
        },
        "Mutability": {
            "type": "object",
            "required": [
                "kind"
            ],
            "additionalProperties": false,
            "properties": {
                "kind": {
                    "type": "string",
                    "enum": [
                        "MutMutable",
                        "Mut",
                        "MutImmutable",
                        "Not"
                    ]
                }
            }
        },
        "Abi": {
            "description": "Calling convention for this function",
            "type": "object",
            "required": [
                "kind"
            ],
            "properties": {
                "kind": {
                    "type": "string"
                }
            }
        }
    }
}